loadaudio/__init__.py
loadaudio/utils.py
loadaudio-1.0.0.dist-info/LICENSE
loadaudio-1.0.0.dist-info/METADATA
loadaudio-1.0.0.dist-info/WHEEL
loadaudio-1.0.0.dist-info/top_level.txt
loadaudio-1.0.0.dist-info/RECORD
