Metadata-Version: 2.1
Name: loadaudio
Version: 1.0.0
Summary: a python package to effortlessly load audio and convert audio to different formats.
Home-page: https://github.com/KingNish24/loadaudio
Author: Nishith Jain
Author-email: kingnish24@gmail.com
Classifier: Programming Language :: Python :: 3
Classifier: License :: OSI Approved :: MIT License
Classifier: Operating System :: OS Independent
License-File: LICENSE
Requires-Dist: setuptools
Requires-Dist: pydub
Requires-Dist: requests
Requires-Dist: numpy
Requires-Dist: wheel
Requires-Dist: typing
